[
  {
    "topic": "scan",
    "file": "build/commands/scan.md",
    "header": "Run scan"
  },
  {
    "topic": "init",
    "file": "build/commands/init.md",
    "header": "Init Lava project"
  },
  {
    "topic": "version",
    "file": "build/commands/version.md",
    "header": "Print Lava version"
  },
  {
    "topic": "environment",
    "file": "build/helpdoc/environment.md",
    "header": "Environment variables"
  },
  {
    "topic": "lava.yaml",
    "file": "build/helpdoc/configuration.md",
    "header": "Configuration file format"
  },
  {
    "topic": "metrics",
    "file": "build/helpdoc/metrics.md",
    "header": "Metrics collection"
  }
]
